pyroll/zouhar_contact.py
pyroll_zouhar_contact-3.0.0.post0.dist-info/METADATA
pyroll_zouhar_contact-3.0.0.post0.dist-info/WHEEL
pyroll_zouhar_contact-3.0.0.post0.dist-info/licenses/LICENSE
pyroll_zouhar_contact-3.0.0.post0.dist-info/RECORD
