Metadata-Version: 2.3
Name: pyroll-zouhar-contact
Version: 3.0.0.post0
Summary: Plugin for PyRolL providing contact area estimation by G. Zouhar.
Project-URL: Homepage, https://pyroll.readthedocs.io
Project-URL: Repository, https://github.com/pyroll-project/pyroll-zouhar-contact
Project-URL: Documentation, https://github.com/pyroll-project/pyroll-zouhar-contact/blob/main/docs/docs.pdf
Author-email: Max Weiner <max.weiner@imf.tu-freiberg.de>, Christoph Renzing <christoph.renzing@imf.tu-freiberg.de>, Richard Pfeifer <richard.pfeifer@imf.tu-freiberg.de>
Classifier: Intended Audience :: Manufacturing
Classifier: Intended Audience :: Science/Research
Classifier: Operating System :: OS Independent
Classifier: Topic :: Scientific/Engineering
Requires-Python: >=3.9
Requires-Dist: pyroll-core~=3.0
